{
  "frames": {
    "catalyst-steampunk": {
      "frame": {
        "x": 0,
        "y": 0,
        "w": 420,
        "h": 720
      }
    },
    "catalyst-forest": {
      "frame": {
        "x": 420,
        "y": 0,
        "w": 420,
        "h": 720
      }
    },
    "catalyst-skyward": {
      "frame": {
        "x": 840,
        "y": 0,
        "w": 420,
        "h": 720
      }
    },
    "catalyst-sacrificial": {
      "frame": {
        "x": 1260,
        "y": 0,
        "w": 420,
        "h": 720
      }
    },
    "catalyst-dreams": {
      "frame": {
        "x": 0,
        "y": 720,
        "w": 420,
        "h": 720
      }
    },
    "catalyst-magic-guide": {
      "frame": {
        "x": 420,
        "y": 720,
        "w": 420,
        "h": 720
      }
    },
    "catalyst-flowing-purity": {
      "frame": {
        "x": 840,
        "y": 720,
        "w": 420,
        "h": 720
      }
    },
    "catalyst-eternal-flow": {
      "frame": {
        "x": 1260,
        "y": 720,
        "w": 420,
        "h": 720
      }
    },
    "catalyst-remembrance": {
      "frame": {
        "x": 0,
        "y": 1440,
        "w": 420,
        "h": 720
      }
    },
    "catalyst-sacred-winds": {
      "frame": {
        "x": 420,
        "y": 1440,
        "w": 420,
        "h": 720
      }
    }
  },
  "meta": {
    "image": "weapon-catalyst.webp",
    "size": {
      "w": 1680,
      "h": 2160
    },
    "scale": "1",
    "path": "assets\\images\\cards\\weapon\\catalyst\\weapon-catalyst.webp"
  }
}